{"commitInfo":{"timestamp":1780146657098,"operation":"WRITE","operationParameters":{"mode":"Overwrite","partitionBy":"[]"},"readVersion":0,"isolationLevel":"Serializable","isBlindAppend":false,"operationMetrics":{"numFiles":"1","numOutputRows":"13","numOutputBytes":"1235"},"engineInfo":"Apache-Spark/3.5.1 Delta-Lake/3.2.0","txnId":"e0f6c552-5e2f-4e28-a4b2-8329e35e824a"}}
{"add":{"path":"part-00000-2bb0fc56-f9c2-4020-83c3-693c411d6ff5-c000.snappy.parquet","partitionValues":{},"size":1235,"modificationTime":1780146640469,"dataChange":true,"stats":"{\"numRecords\":13,\"minValues\":{\"kota\":\"BANYUWANGI\",\"kategori_aqi\":\"Baik\",\"jumlah\":1},\"maxValues\":{\"kota\":\"SURABAYA\",\"kategori_aqi\":\"Sedang\",\"jumlah\":7},\"nullCount\":{\"kota\":0,\"kategori_aqi\":0,\"jumlah\":0}}"}}
{"remove":{"path":"part-00000-d3b0fbd1-bcc5-474c-99f8-078f042b2dba-c000.snappy.parquet","deletionTimestamp":1780146657096,"dataChange":true,"extendedFileMetadata":true,"partitionValues":{},"size":1235}}
